nbsrc/__init__.py
nbsrc/cli.py
nbsrc/nbsrc.py
nbsrc/srcexporter.py
nbsrc-0.4.0.dist-info/METADATA
nbsrc-0.4.0.dist-info/RECORD
nbsrc-0.4.0.dist-info/WHEEL
nbsrc-0.4.0.dist-info/entry_points.txt
nbsrc-0.4.0.dist-info/top_level.txt
tests/__init__.py
tests/test_cli.py
tests/test_nbconvert.py
tests/test_readme.py
tests/utils.py
