Metadata-Version: 2.1
Name: nbsrc
Version: 0.4.0
Summary: Jupyter notebooks from/to python and R scripts
Home-page: https://github.com/mwouts/nbsrc
Author: Marc Wouts
Author-email: marc.wouts@gmail.com
License: MIT
Platform: UNKNOWN
Classifier: Development Status :: 4 - Beta
Classifier: Environment :: Console
Classifier: Framework :: Jupyter
Classifier: Intended Audience :: Science/Research
Classifier: Programming Language :: Python
Classifier: Topic :: Text Processing :: Markup
Classifier: Programming Language :: Python
Classifier: Programming Language :: Python :: 2.7
Classifier: Programming Language :: Python :: 3
Classifier: Programming Language :: Python :: 3.4
Classifier: Programming Language :: Python :: 3.5
Classifier: Programming Language :: Python :: 3.6
Requires-Dist: nbformat (>=4.0.0)
Requires-Dist: mock
Requires-Dist: pyyaml
